tensor_c.cpython-313-darwin.so
mx/__init__.py
mx/functional.py
mx/linear.py
mx/module.py
mx/norm.py
tensor/__init__.py
tensor/tensor.py
qkmx-0.1.6.dist-info/METADATA
qkmx-0.1.6.dist-info/WHEEL
qkmx-0.1.6.dist-info/top_level.txt
qkmx-0.1.6.dist-info/RECORD
