Metadata-Version: 2.4
Name: qkmx
Version: 0.1.6
Summary: Pure C accelerated matrix operations for LLMs
Author-email: Michael Williams <mww565@icloud.com>
Project-URL: Homepage, https://github.com/micwill755/qmx
Project-URL: Repository, https://github.com/micwill755/qmx
Requires-Python: >=3.7
Requires-Dist: qkbind
Dynamic: requires-python
